NightBat/__init__.py
NightBat-0.0.1.dist-info/LICENSE
NightBat-0.0.1.dist-info/METADATA
NightBat-0.0.1.dist-info/WHEEL
NightBat-0.0.1.dist-info/top_level.txt
NightBat-0.0.1.dist-info/RECORD
