Metadata-Version: 2.1
Name: NightBat
Version: 0.0.1
Summary: NightBat
Home-page: https://github.com/Server04/NightBat
Author: Nong Hoang Vu
Author-email: Nong Hoang Vu <nonghoangvu04@gmail.com>
License: Copyright (c) 2018 The Python Packaging Authority        
Project-URL: Homepage, https://github.com/Server04/NightBat
Project-URL: Bug Tracker, https://github.com/Server04/NightBat
Classifier: Programming Language :: Python :: 3
Classifier: License :: OSI Approved :: MIT License
Classifier: Operating System :: OS Independent
Requires-Python: >=3.7
License-File: LICENSE
